{"api_index.md":"DNLFP9li","charts_area-stacked.md":"DyqrNFNl","charts_area.md":"BC2x8pEV","charts_bar-grouped.md":"Bg6_Dsjc","charts_bar-horizontal.md":"C6_C9MKr","charts_bar-multi.md":"BMj6PRvY","charts_bar-split.md":"BYzdiIi6","charts_bar-stacked.md":"00WgzGPs","charts_bar-vertical.md":"AfUlAHyU","charts_column-stacked.md":"3f0Wn0UP","charts_donut.md":"BD2ya_58","charts_index.md":"CdJyBb6v","charts_line-multi.md":"GujzkPfO","charts_line.md":"eA0KF8ve","charts_pie.md":"CZze7gJP","guide_accessibility.md":"BkyG-Q-9","guide_data-transforms.md":"C0YNArAd","guide_dsl-editor.md":"SPKGkvUQ","guide_embed.md":"DoP_vyHf","guide_getting-started.md":"Bw3QKFN0","guide_palettes.md":"CpXkWukw","guide_scenes.md":"B9z86pua","handbook_accessibility.md":"B_KLrb80","handbook_annotations.md":"ClwOIa9z","handbook_anti-patterns.md":"fSOOWZqM","handbook_axes.md":"DzKt9jp2","handbook_choosing.md":"D25QjC5J","handbook_color.md":"XlCxWmTe","handbook_design-principles.md":"BiMgG8Qb","handbook_frame-elements.md":"BDg4YB-W","handbook_index.md":"DyiuO5C3","handbook_labels.md":"CSdkhXTc","handbook_tooltips.md":"Boeb_J7o","handbook_typography.md":"e3DU3iA6","index.md":"N_6-pjeZ","spec_dsl.md":"DQ5MUN4d"}
